microkinetic_toolkit/__init__.py
microkinetic_toolkit/dump_json.py
microkinetic_toolkit/reaction.py
microkinetic_toolkit/reaction_for_db.py
microkinetic_toolkit/reactions.py
microkinetic_toolkit/reactions_base.py
microkinetic_toolkit/reactions_for_db.py
microkinetic_toolkit/data/__init__.py
microkinetic_toolkit/openfoam/__init__.py
microkinetic_toolkit/openfoam/make_openfoam_input.py
microkinetic_toolkit/preparation/__init__.py
microkinetic_toolkit/preparation/add_vol_and_entropy.py
microkinetic_toolkit/preparation/preparation.py
microkinetic_toolkit/preparation/rot_control.py
microkinetic_toolkit/visualization/__init__.py
microkinetic_toolkit/visualization/colors.py
microkinetic_toolkit/visualization/graph.py
microkinetic_toolkit-0.0.1.dist-info/LICENSE
microkinetic_toolkit-0.0.1.dist-info/METADATA
microkinetic_toolkit-0.0.1.dist-info/WHEEL
microkinetic_toolkit-0.0.1.dist-info/top_level.txt
microkinetic_toolkit-0.0.1.dist-info/RECORD
