Metadata-Version: 2.1
Name: microkinetic-toolkit
Version: 0.0.1
Summary: Python library for microkinetic analysis in catalytic chemistry.
Home-page: https://github.com/atsushi-ishikawa/microkinetic_toolkit
Download-URL: https://github.com/atsushi-ishikawa/microkinetic_toolkit
Author: Atsushi Ishikawa, Haruyuki Oda
Author-email: ishikawa.atsushi@nims.go.jp
Maintainer: Atsushi Ishikawa
Maintainer-email: ishikawa.atsushi@nims.go.jp
License: MIT
License-File: LICENSE
